Metadata-Version: 2.1
Name: processamento-video
Version: 1.0
Summary: Este pacote irá fornecer ferramentas de processamento de vídeo
Author: DJalme
Author-email: dj@hotmail.com
Keywords: camera,video,processamento
License-File: licence.txt
